Workbook

Sheet Version Log
A1: Timestamp | B1: Version | C1: User | D1: Note
A2: 46157.583 | B2: 1.00.00 | C2: ryan.k@smokypeak.tech | D2: Version reset to 1.00.00 — first publish.
A3: 46157.585 | B3: 0.00.01 | C3: ryan.k@smokypeak.tech | D3: Line edit detected on row 38, col 1 of Consumables and Shop Supplies
A4: 46157.585 | B4: 0.00.02 | C4: ryan.k@smokypeak.tech | D4: Line edit detected on row 38, col 2 of Consumables and Shop Supplies
A5: 46157.585 | B5: 0.00.03 | C5: ryan.k@smokypeak.tech | D5: Line edit detected on row 38, col 3 of Consumables and Shop Supplies
A6: 46157.588 | B6: 0.00.04 | C6: ryan.k@smokypeak.tech | D6: Line edit on row 38, col 1
A7: 46157.588 | B7: 0.00.05 | C7: ryan.k@smokypeak.tech | D7: Line edit on row 38, col 2
A8: 46157.588 | B8: 0.00.06 | C8: ryan.k@smokypeak.tech | D8: Line edit on row 38, col 3
A9: 46157.588 | B9: 0.00.07 | C9: ryan.k@smokypeak.tech | D9: Line edit on row 38, col 4
A10: 46157.589 | B10: 0.00.08 | C10: ryan.k@smokypeak.tech | D10: Line edit on row 38, col 5
A11: 46157.589 | B11: 0.00.09 | C11: ryan.k@smokypeak.tech | D11: Line edit on row 38, col 6

Sheet Hourly Labor Rates
A1: Cabin Services Labor Rate Inputs
A2: Burden Multiplier | B2: 1.85
A3: Standard Billing Multiplier | B3: 1.4
A4: After Hours and Emergency Multiplier | B4: 1.45
A5: Holiday Rate Multiplier | B5: 1.75
A6: Discounted Rate Multiplier | B6: 0.9
A8: Position Title | B8: SKU | C8: Base Hourly Rate | D8: Actual Cost of Labor | E8: Standard Billing Rate | F8: After Hours and Emergency Rate | G8: Holiday Rate | H8: Discounted Rate | I8: Labor Rate Percentage
A9: Field Technician | B9: LAB-CBN-FLD-SPC | C9: 18 | D9: =C9*$B$2 -> 33.3 | E9: =D9*$B$3 -> 46.62 | F9: =E9*$B$4 -> 67.599 | G9: =E9*$B$5 -> 81.585 | H9: =E9*$B$6 -> 41.958 | I9: 0.7
A10: Senior Field Technician | B10: LAB-CBN-SFT-SPC | C10: 22 | D10: =C10*$B$2 -> 40.7 | E10: =D10*$B$3 -> 56.98 | F10: =E10*$B$4 -> 82.621 | G10: =E10*$B$5 -> 99.715 | H10: =E10*$B$6 -> 51.282 | I10: 0.2
A11: Contractor Coordination | B11: LAB-CBN-CCO-SPC | C11: 35 | D11: =C11*$B$2 -> 64.75 | E11: =D11*$B$3 -> 90.65 | F11: =E11*$B$4 -> 131.4425 | G11: =E11*$B$5 -> 158.6375 | H11: =E11*$B$6 -> 81.585 | I11: 0
A12: Inspector | B12: LAB-CBN-INS-SPC | C12: 20 | D12: =C12*$B$2 -> 37 | E12: =D12*$B$3 -> 51.8 | F12: =E12*$B$4 -> 75.11 | G12: =E12*$B$5 -> 90.65 | H12: =E12*$B$6 -> 46.62 | I12: 0.1
A13: Total Labor Rate Percentage | I13: =I9+I10+I12 -> 1
A15: Notes Block
A16: Burden multiplier of 1.85 covers payroll taxes, workers compensation, general liability, vehicle and equipment overhead, and administrative costs
A17: Standard billing rate reflects residential and STR service market rates for East Tennessee
A18: After hours and emergency rates apply to any work performed outside standard business hours or dispatched as an emergency response
A19: Holiday rates apply to work performed on company observed holidays
A20: Discounted rate is available for high volume contract clients or preferred account relationships at management discretion
A21: Contractor Coordination is billed at a flat rate independently from field labor and is not included in project labor percentage calculations
A22: Labor Rate Percentages are used in quoting to calculate blended labor totals and should always sum to 100% across billable field positions

Sheet Maintenance Plan Rates
A1: Maintenance Plan Rates
A2: Description | B2: SKU | C2: # of Bedrooms | D2: Maximum Bathrooms | E2: Rate
A3: Standard Studio or 1 Bedroom | B3: MP-1BE-1BA-STD | C3: 1 | D3: 1 | E3: 125
A4: Standard 2 Bedroom | B4: MP-2BE-2BA-STD | C4: 2 | D4: 2 | E4: 150
A5: Standard 3 Bedroom | B5: MP-3BE-3BA-STD | C5: 3 | D5: 3 | E5: 175
A6: Standard 4 bedroom | B6: MP-4BE-4BA-STD | C6: 4 | D6: 4 | E6: 210
A7: Standard 5 Bedroom | B7: MP-5BE-5BA-STD | C7: 5 | D7: 5 | E7: 250
A8: Custom Quote Special Property | B8: MP-CUS-QUO-SPL | C8: - | D8: - | E8: Quoted

Sheet Inspection Plan Rates 
A1: Inspection Plan Rates
A2: Description | B2: SKU | C2: # of Bedrooms | D2: Maximum Bathrooms | E2: Rate
A3: Standard Studio or 1 Bedroom | B3: CIP-1BE-1BA-STD | C3: 1 | D3: 1 | E3: 95
A4: Standard 2 Bedroom | B4: CIP-2BE-2BA-STD | C4: 2 | D4: 2 | E4: 110
A5: Standard 3 Bedroom | B5: CIP-3BE-3BA-STd | C5: 3 | D5: 3 | E5: 125
A6: Standard 4 bedroom | B6: CIP-4BE-4BA-STD | C6: 4 | D6: 4 | E6: 150
A7: Standard 5 Bedroom | B7: CIP-5BE-5BA-STD | C7: 5 | D7: 5 | E7: 175
A8: Custom Quote Special Property | B8: CIP-CUS-QUO-SPL | C8: - | D8: - | E8: Quoted

Sheet Full-Service Plan Rates
A1: Full-Service Plan Rates (Maintenance & Inspection)
A2: Description | B2: SKU | C2: # of Bedrooms | D2: Maximum Bathrooms | E2: Rate
A3: Standard Studio or 1 Bedroom | B3: FSP-1BE-1BA-STD | C3: 1 | D3: 1 | E3: 185
A4: Standard 2 Bedroom | B4: FSP-2BE-2BS-STD | C4: 2 | D4: 2 | E4: 215
A5: Standard 3 Bedroom | B5: FSP-3BE-3BA-STD | C5: 3 | D5: 3 | E5: 250
A6: Standard 4 bedroom | B6: FSP-4BE-4BA-STD | C6: 4 | D6: 4 | E6: 295
A7: Standard 5 Bedroom | B7: FSP-5BE-5BA-STD | C7: 5 | D7: 5 | E7: 345
A8: Custom Quote Special Property | B8: FSP-CUS-QUO-SPL | C8: - | D8: - | E8: Quoted

Sheet Complexity Multipliers 
A1: Complexity Multipliers
A2: Description | B2: Multiplier Category | C2: Multiplier Type | D2: Applied Too? | E2: Modification Rate | F2: Note and Rules
A3: Additional Bathroom | B3: Amenity | C3: Fixed Rate | D3: Base Package Rate | E3: 8 | F3: An additional bathroom is any full or partial bathroom that exists beyond the primary bathroom associated with the base bedroom count of the property. Includes all fixture types such as toilets, sinks, showers, and tubs. Each additional bathroom adds unclassified square footage and fixture count to the inspection and maintenance scope requiring additional time on every visit.
A4: On-Premise Swim Spa or Hot Tub | B4: Amenity | C4: Fixed Rate | D4: Base Package Rate | E4: 12 | F4: A swim spa or hot tub is any on-premise hydrotherapy or recreational water fixture that requires function testing during inspections. Includes verification of heating elements, jet functionality, water clarity, cover condition, and accessible equipment. Repairs and chemical servicing must be completed by a certified vendor and are not included in the base inspection scope.
A5: On-Premise Sauna | B5: Amenity | C5: Fixed Rate | D5: Base Package Rate | E5: 12 | F5: An on-premise sauna is any dedicated dry or steam heat enclosure located on the property that requires function testing during inspections. Includes verification of heating elements, controls, ventilation, and structural condition of the enclosure. Repairs to heating or electrical components must be completed by a certified vendor and are not included in the base inspection scope.
A6: In-Unit Spa Tub | B6: Amenity | C6: Fixed Rate | D6: Base Package Rate | E6: 10 | F6: An in-unit spa tub is any jetted or whirlpool style bathtub installed within the primary dwelling that requires function testing beyond a standard bathtub inspection. Includes verification of jet functionality, drain performance, and visible plumbing access points. Repairs to jet systems or plumbing must be completed by a certified vendor and are not included in the base inspection scope.
A7: Vaulted Ceilings | B7: Structural | C7: Percentage Basis | D7: Base Package Rate | E7: 0.025 | F7: Vaulted ceilings are any ceiling structure that exceeds standard height and requires specialized access for routine maintenance tasks such as light fixture servicing, window cleaning, or ceiling fan maintenance. The percentage multiplier reflects the increased labor cost and access complexity on visits where elevated work is required and is spread across all billing cycles to balance the irregular nature of those tasks.
A8: Gas Fireplace | B8: Amenity | C8: Percentage Basis | D8: Base Package Rate | E8: 0.04 | F8: A gas fireplace is any permanently installed gas fired hearth appliance that requires function testing and visual inspection during each visit. Includes verification of ignition, flame presentation, ventilation, and accessible gas connections. Repairs to gas lines, ignition systems, or ventilation components must be completed by a certified vendor and are not included in the base inspection scope.
A9: Wood Burning Fireplace | B9: Amenity | C9: Percentage Basis | D9: Base Package Rate | E9: 0.025 | F9: A wood burning fireplace is any permanently installed solid fuel hearth appliance that requires periodic function and ventilation testing. A bi-annual inspection of the firebox, damper, and accessible flue components is included within the monthly multiplier rate. The percentage reflects the ongoing monitoring cost across all billing cycles with the bi-annual inspection absorbed into that recurring charge rather than billed as a separate line item.
A10: HVAC Access in Attic or Crawl Space | B10: Mechanical | C10: Percentage Basis | D10: Base Package Rate | E10: 0.04 | F10: An attic or crawl space HVAC configuration is any heating or cooling system where primary components, ductwork, or air handlers are located in a space requiring non-standard access. Includes any system where the inspector must enter or access a confined, elevated, or below grade space to complete routine maintenance tasks. The percentage multiplier reflects the increased time and physical demands associated with access limitations on every qualifying visit.
A11: Smart Home Integrations | B11: Technology | C11: Percentage Basis | D11: Base Package Rate | E11: 0.08 | F11: Smart home integrations are any network connected control systems installed on the property including but not limited to smart thermostats, automated lighting, connected locks, security systems, motorized shades, or whole home audio and video systems. The percentage multiplier reflects the increased scope of inspection and the technical knowledge required to verify system functionality, connectivity, and guest readiness on every visit.
A12: Home Theater or Luxury Living Rooms | B12: Amenity | C12: Fixed Rate | D12: Base Package Rate | E12: 18 | F12: A home theater or luxury living room is any dedicated entertainment space containing premium audio, video, or experiential equipment beyond standard residential fixtures. Includes verification of display functionality, audio system operation, streaming device connectivity, seating condition, and any specialty lighting or control systems. The flat fee reflects the additional time required to inspect and document all entertainment package components on every visit.
A13: ADU Dwelling | B13: Amenity | C13: Fixed Rate | D13: Base Package Rate | E13: 75 | F13: An ADU is a secondary dwelling unit on the same property that contains its own independent living fixtures including sleeping, cooking, and bathroom facilities. Typically presented as a studio or apartment style unit. Does not apply to bunk rooms, bonus rooms, or overflow sleeping areas that share primary dwelling amenities. Must be paired with the primary dwelling service plan to qualify for the ADU multiplier rate.
A14: Auxillery Shed or Garage | B14: Outdoor | C14: Fixed Rate | D14: Base Package Rate | E14: 8 | F14: An auxiliary shed or garage is any detached or semi-detached outbuilding located on the property that falls outside the footprint of the primary dwelling and requires independent inspection during each visit. Includes verification of structural condition, door and lock functionality, electrical if present, and general interior condition. Does not apply to attached garages already captured within the primary dwelling square footage.
... A22: Seasonal Access Limitations | B22: Access | C22: Percentage Basis | D22: Base Package Rate | E22: 0.085 | F22: Seasonal access limitations apply to any property where primary access routes are subject to restriction due to terrain, weather conditions, road grade, or requirements for four wheel drive or high clearance vehicles. The percentage multiplier reflects the increased travel time, vehicle wear, and operational complexity associated with servicing properties under limited or restricted access conditions and applies for the duration of any qualifying access period.

Sheet Consumables and Shop Supplies
A1: Consumables and Shop Supplies
A2: Product Description | B2: Manufacturer | C2: Part Number | D2: SKU | E2: Waste Factor % | F2: Units | G2: Unit Cost | H2: Sale Price | I2: Labor Units | J2: Labor Rate
A3: 128 FL OZ DISTILLED WHITE VINEGAR | B3: MEMBERS MARK | C3: 789344 | D3: CON-VIN-128-MEM | E3: 0.025 | F3: FLUID OUNCES | G3: 0.06 | H3: =G3*1.3 -> 0.078 | I3: 0.025 | J3: ='Hourly Labor Rates'!$E$9 -> 46.62
A4: STANDARD AA BATTERY | B4: DURACELL | C4: MN15P36 | D4: CON-BAT-AA-DUR | E4: 0 | F4: EACH | G4: 0.84 | H4: =G4*1.3 -> 1.092 | I4: 0.025 | J4: ='Hourly Labor Rates'!$E$9 -> 46.62
A5: STANDARD AAA BATTERY | B5: DURACELL | C5: MN24P36 | D5: CON-BAT-AAA-DUR | E5: 0 | F5: EACH | G5: 0.72 | H5: =G5*1.3 -> 0.936 | I5: 0.025 | J5: ='Hourly Labor Rates'!$E$9 -> 46.62
A6: STANDARD 9V BATTERY | B6: DURACELL | C6: MN1604BKD | D6: CON-BAT-9V-DUR | E6: 0 | F6: EACH | G6: 2.58 | H6: =G6*1.3 -> 3.354 | I6: 0.033 | J6: ='Hourly Labor Rates'!$E$9 -> 46.62
A7: STANDARD CR123A BATTERY | B7: AMAZON BASICS | C7: CR123AB/24FB | D7: CON-BAT-123-AMZ | E7: 0 | F7: EACH | G7: 1.66 | H7: =G7*1.3 -> 2.158 | I7: 0.025 | J7: ='Hourly Labor Rates'!$E$9 -> 46.62
A8: STANDARD CR2032 COIN BATTERY | B8: PHILLIPS | C8: CR2032 | D8: CON-BAT-203-PHI | E8: 0 | F8: EACH | G8: 0.44 | H8: =G8*1.3 -> 0.572 | I8: 0.025 | J8: ='Hourly Labor Rates'!$E$9 -> 46.62
A9: STANDARD D BATTERY | B9: DURACELL | C9: MN1300 | D9: CON-BAT-D-DUR | E9: 0.05 | F9: EACH | G9: 1.61 | H9: =G9*1.3 -> 2.093 | I9: 0.025 | J9: ='Hourly Labor Rates'!$E$9 -> 46.62
A10: STANDARD C BATTERY | B10: DURACELL | C10: MN1400 | D10: CON-BAT-C-DUR | E10: 0.05 | F10: EACH | G10: 1.75 | H10: =G10*1.3 -> 2.275 | I10: 0.025 | J10: ='Hourly Labor Rates'!$E$9 -> 46.62
A11: RECHARGEABLE AA BATTERY | B11: AMAZON BASICS | C11: 210AAHCB | D11: CON-RBT-AA-AMZ | E11: 0 | F11: EACH | G11: 1.07 | H11: =G11*1.3 -> 1.391 | I11: 0.025 | J11: ='Hourly Labor Rates'!$E$9 -> 46.62
A12: RECHARGEABLE AAA BATTERY | B12: AMAZON BASICS | C12: 85AAAHCB | D12: CON-RBT-AAA-AMZ | E12: 0 | F12: EACH | G12: 0.6 | H12: =G12*1.3 -> 0.78 | I12: 0.025 | J12: ='Hourly Labor Rates'!$E$9 -> 46.62
A13: RECHARGEABLE 9V BATTERY | B13: AMAZON BASICS | C13: COR00003 | D13: CON-RBT-9V-AMZ | E13: 0 | F13: EACH | G13: 3.74 | H13: =G13*1.3 -> 4.862 | I13: 0.025 | J13: ='Hourly Labor Rates'!$E$9 -> 46.62
A14: RECHARGEABLE C BATTERY | B14: AMAZON BASICS | C14: COR00001 | D14: CON-RBT-C-AMZ | E14: 0 | F14: EACH | G14: 4.09 | H14: =G14*1.3 -> 5.317 | I14: 0.025 | J14: ='Hourly Labor Rates'!$E$9 -> 46.62
A15: RECHARGEABLE D BATTERY | B15: AMAZON BASICS | C15: COR00002 | D15: CON-RBT-D-AMZ | E15: 0 | F15: EACH | G15: 5.95 | H15: =G15*1.3 -> 7.735 | I15: 0.025 | J15: ='Hourly Labor Rates'!$E$9 -> 46.62
... A20: 65W DAYLIGHT WHITE 5000K BR30 LED BULB | B20: AMAZON BASICS | C20: FG-03453 | D20: CON-BR30-DLW-AMZ | E20: 0 | F20: EACH | G20: 1.62 | H20: =G20*1.3 -> 2.106 | I20: 0.05 | J20: ='Hourly Labor Rates'!$E$9 -> 46.62
A21: 60W DAYLIGHT WHITE 5000K B10 LED BULB | B21: SYLVANIA | C21: 40207 | D21: CON-B10-DLW-SYL | E21: 0 | F21: EACH | G21: 2.06 | H21: =G21*1.3 -> 2.678 | I21: 0.05 | J21: ='Hourly Labor Rates'!$E$9 -> 46.62
A22: 50W WARM WHITE 3000K PAR16 LED BULB | B22: PHILLIPS | C22: 570762 | D22: CON-PAR-WW-PHI | E22: 0 | F22: EACH | G22: 3.89 | H22: =G22*1.3 -> 5.057 | I22: 0.05 | J22: ='Hourly Labor Rates'!$E$9 -> 46.62
A23: 45W SOFT WHITE 2700K R20 LED BULB | B23: PHILLIPS | C23: 576496 | D23: CON-R20-SW-PHI | E23: 0 | F23: EACH | G23: 5.95 | H23: =G23*1.3 -> 7.735 | I23: 0.05 | J23: ='Hourly Labor Rates'!$E$9 -> 46.62
A24: 45W DAYLIGHT WHITE 5000K R20 LED BULB | B24: PHILLIPS | C24: 576488 | D24: CON-R20-DLW-PHI | E24: 0 | F24: EACH | G24: 5.95 | H24: =G24*1.3 -> 7.735 | I24: 0.05 | J24: ='Hourly Labor Rates'!$E$9 -> 46.62
A25: 50W WARM WHITE 3000K MR16 LED BULB | B25: AMAZON BASICS | C25: FG-03434 | D25: CON-MR16-WW-AMZ | E25: 0 | F25: EACH | G25: 2.65 | H25: =G25*1.3 -> 3.445 | I25: 0.05 | J25: ='Hourly Labor Rates'!$E$9 -> 46.62
A26: 50W DAYLIGHT WHITE 5000K MR16 LED BULB | B26: AMAZON BASICS | C26: FG-03435 | D26: CON-MR16-DLW-AMZ | E26: 0 | F26: EACH | G26: 2.65 | H26: =G26*0.3 -> 0.795 | I26: 0.05 | J26: ='Hourly Labor Rates'!$E$9 -> 46.62
A27: RID-X SEPTIC TANK TREATMENT PODS | B27: RID-X | C27: 1920084249 | D27: CON-RID-SEP-TRM | E27: 0 | F27: EACH | G27: 4.53 | H27: =G27*1.3 -> 5.889 | I27: 0.025 | J27: ='Hourly Labor Rates'!$E$9 -> 46.62
A28: KITCHEN PAPER TOWELS 2-PLY | B28: GENUINE JOE | C28: GJO24085 | D28: CON-2PY-PT-GEJ | E28: 0.1 | F28: EACH | G28: 1.21 | H28: =G28*1.3 -> 1.573 | I28: 0.02 | J28: ='Hourly Labor Rates'!$E$9 -> 46.62
A29: 42 GALLON 3MIL BLACK GARBAGE BAG | B29: COMMANDER | C29: 735692035336 | D29: CON-3MI-BLA-COM | E29: 0.05 | F29: EACH | G29: 0.79 | H29: =G29*1.3 -> 1.027 | I29: 0.02 | J29: ='Hourly Labor Rates'!$E$9 -> 46.62
A30: KITCHEN & BATH KWIK SEAL PLUS WHITE SEALANT | B30: DAP | C30: 18510 | D30: CON-KWI-WHI-KB-DAP | E30: 0.15 | F30: EACH | G30: 7.89 | H30: =G30*1.3 -> 10.257 | I30: 1.25 | J30: ='Hourly Labor Rates'!$E$9 -> 46.62
A31: KITCHEN & BATH ADVANCED SILICONE CLEAR | B31: GE | C31: 2812562 | D31: CON-SIL-CLE-KB-GE | E31: 0.15 | F31: EACH | G31: 10.97 | H31: =G31*1.3 -> 14.261 | I31: 1.25 | J31: ='Hourly Labor Rates'!$E$9 -> 46.62
A32: WINDOW & DOOR SUPREME SILICONE WHITE | B32: GE | C32: 2733730 | D32: CON-SIL-WHI-WD-GE | E32: 0.15 | F32: EACH | G32: 12.67 | H32: =G32*1.3 -> 16.471 | I32: 1.25 | J32: ='Hourly Labor Rates'!$E$9 -> 46.62
A33: WINDOW & DOOR SUPREME SILICONE CLEAR | B33: GE | C33: 2814816 | D33: CON-SIL-CLE-WD-GE | E33: 0.15 | F33: EACH | G33: 12.67 | H33: =G33*1.3 -> 16.471 | I33: 1.25 | J33: ='Hourly Labor Rates'!$E$9 -> 46.62
A34: PROPANE TANK EXCHANGE STANDARD 20LBS TANK (SERVICE FEE) | B34: SMOKY PEAK CS | C34: 20LB-LP | D34: SVC-PRO-EXC-SCS | E34: 0 | F34: EACH | G34: 19.23 | H34: =G34*1.3 -> 24.999 | I34: 0.1 | J34: ='Hourly Labor Rates'!$E$9 -> 46.62
A35: LIQUID PROPANE (PRODUCT PASS-THRU) | B35: ACE HARDWARE | C35: LP-XLBS | D35: CON-PRO-FIL-RET | E35: 0 | F35: EACH | G35: MRKT RATE | H35: MRKT RATE | I35: 0.05 | J35: ='Hourly Labor Rates'!$E$9 -> 46.62
A36: PROPANE REFILL OVERSIZE TANKS 21LBS-100LBS (SERVICE FEE) | B36: SMOKY PEAK CS | C36: XL-LP | D36: SVC-PRO-REF-LRG | E36: 0 | F36: EACH | G36: 30.77 | H36: =G36*1.3 -> 40.001 | I36: 0.15 | J36: ='Hourly Labor Rates'!$E$9 -> 46.62
A37: PROPANE TANK DISPOSAL FEE (SERVICE FEE) | B37: SMOKY PEAK CS | C37: PRO-DIS | D37: SVC-PRO-DIS-EXP | E37: 0 | F37: EACH | G37: 19.23 | H37: =G37*1.3 -> 24.999 | I37: 0.05 | J37: ='Hourly Labor Rates'!$E$9 -> 46.62
A39: Notes Block
A40: Column J Labor Rate is dynamically linked to the Field Technician Standard Billing Rate on the Hourly Labor Rates tab. Any change to the Field Technician base rate or burden and billing multipliers on the labor rate sheet will automatically recalculate the labor rate applied to all consumable and shop supply line items. Do not manually edit column J values as they will be overwritten by the linked formula.

Sheet Summary & Index
A1: Sheet Summary & Version Index
A3: Current Version | B3: Last Modified | C3: Block 1 (Major) Trigger | D3: Block 2 (Minor) Trigger | E3: Block 3 (Line) Trigger | F3: Status
A4: 0.00.09 | B4: 46157 | C4: New pages, tables, or 4+ page edits | D4: Small revisions, formula/rate changes | E4: Line edits, adding to data structures | F4: Active
A6: Workbook-Wide Notes
A7: This workbook uses dynamic links to automatically calculate rates. The Consumables and Shop Supplies tab is dynamically linked to the Field Technician Standard Billing Rate. Version control is managed via the Apps Script menu. Use the Version Counter to increment major, minor, or line edits appropriately.
A11: Tab Index & Descriptions
A12: Tab Name | B12: Description | C12: Primary Use
A13: Hourly Labor Rates | B13: Defines base rates, multipliers, and billing rates for field positions. | C13: Labor Pricing
A14: Complexity Multipliers | B14: Lists multipliers applied to services based on job complexity. | C14: Pricing Modifiers
A15: Full-Service Plan Rates | B15: Flat rates for full-service plans based on property size. | C15: Service Plans
A16: Maintenance Plan Rates | B16: Flat rates for maintenance plans based on property size. | C16: Service Plans
A17: Inspection Plan Rates | B17: Flat rates for inspection plans based on property size. | C17: Service Plans
A18: Consumables and Shop Supplies | B18: Pricing and labor units for materials, dynamically linked to labor rates. | C18: Material Pricing
